konsave/__init__.py
konsave/__main__.py
konsave/conf_kde.yaml
konsave/conf_other.yaml
konsave/config.py
konsave/consts.py
konsave/funcs.py
konsave_urban-0.1.6.dist-info/LICENSE
konsave_urban-0.1.6.dist-info/METADATA
konsave_urban-0.1.6.dist-info/WHEEL
konsave_urban-0.1.6.dist-info/entry_points.txt
konsave_urban-0.1.6.dist-info/top_level.txt
konsave_urban-0.1.6.dist-info/RECORD
