Metadata-Version: 2.1
Name: konsave-urban
Version: 0.1.6
Summary: A program that lets you save your Plasma configuration in an instant!
Home-page: https://www.github.com/urban/konsave/
Author: Andreas Bontozoglou
Author-email: a.bontozoglou@gmail.com
Classifier: License :: OSI Approved :: GNU General Public License v3 or later (GPLv3+)
Classifier: Operating System :: POSIX
Classifier: Environment :: Console
Classifier: Intended Audience :: End Users/Desktop
Classifier: Programming Language :: Python
Requires-Python: >=3.6
License-File: LICENSE
Requires-Dist: PyYaml >=5.4.1
Requires-Dist: tabulate
Provides-Extra: dev
Requires-Dist: aiohttp >=3.7.4 ; extra == 'dev'
Requires-Dist: aiohttp-cors >=0.7.0 ; extra == 'dev'
Requires-Dist: black >=20.8b1 ; extra == 'dev'
Requires-Dist: pylint >=2.7.2 ; extra == 'dev'
Requires-Dist: setuptools ; extra == 'dev'
Requires-Dist: wheel ; extra == 'dev'
Requires-Dist: twine ; extra == 'dev'
